{
	"errordesc": null,
	"errorid": 0,
	"requestid": "MTU5OTY2NDMxMDg3MV84Mjc",
	"vdata": [{
			"img": ["https://tx-free-imgs.acfun.cn/vuUWtmLu08-Uv2Mfe-zmURFz-veIfQ3-URFfim.image?imageslim"],
			"isUpCollege": false,
			"groupid": "MTU5OTY2NDMxMDg3MV84Mjc_0",
			"channel": {
				"name": "搞笑",
				"id": 206
			},
			"verifiedType": 0,
			"title": "爆笑喜剧: 农村美女接到诈骗电话, 差点把骗子气晕, 真是个人才!",
			"duration": 208,
			"requestid": "MTU5OTY2NDMxMDg3MV84Mjc",
			"action": 1,
			"href": "17817154",
			"time": 1599660853000,
			"visit": {
				"banana": 0,
				"stows": 0,
				"comments": 0,
				"danmakuSize": 0,
				"views": 0
			},
			"user": {
				"img": "https://tx-free-imgs.acfun.cn/H35xKyLKDr-F3URZn-MNJjYr-Jnuqum-J7jQVr.jpg?imageslim",
				"contractUp": false,
				"name": "爆笑陈家庄",
				"verifiedType": 0,
				"id": 35310336,
				"verifiedText": ""
			}
		}, {
			"img": ["https://tx-free-imgs.acfun.cn/68GxSnYgsp-2Yjeyq-Iz2Yjy-3Uneum-JjEVnu.jpg?imageslim"],
			"isUpCollege": false,
			"groupid": "MTU5OTY2NDMxMDg3MV84Mjc_1",
			"channel": {
				"name": "搞笑",
				"id": 206
			},
			"verifiedType": 0,
			"title": "沉氏养居场 皮卡嚯嚯米西, 被我制止了",
			"duration": 256,
			"requestid": "MTU5OTY2NDMxMDg3MV84Mjc",
			"action": 1,
			"href": "17817140",
			"time": 1599660788000,
			"visit": {
				"banana": 0,
				"stows": 0,
				"comments": 0,
				"danmakuSize": 0,
				"views": 19
			},
			"user": {
				"img": "https://tx-free-imgs.acfun.cn/r0GHS53tVy-e67nim-Z3MJF3-byiYVr-nYf6r2.jpg?imageslim",
				"contractUp": false,
				"name": "江湖人称玉面小白龙",
				"verifiedType": 0,
				"id": 30010518,
				"verifiedText": ""
			}
		}
	]
}
